{
  "ts_utc": "2026-02-21T22:34:50.097947+00:00",
  "integrity_file": "/workspace/hbot/reports/event_store/integrity_20260221.json",
  "baseline_file": "/workspace/hbot/reports/event_store/baseline_counts.json",
  "stored_total_events": 55202,
  "stored_events_by_stream": {
    "hb.audit.v1": 3,
    "hb.market_data.v1": 13780,
    "hb.risk_decision.v1": 13784,
    "hb.signal.v1": 13715,
    "hb.execution_intent.v1": 13920
  },
  "source_events_by_stream": {
    "hb.market_data.v1": 15172,
    "hb.signal.v1": 15085,
    "hb.ml_signal.v1": 0,
    "hb.risk_decision.v1": 15065,
    "hb.execution_intent.v1": 14980,
    "hb.audit.v1": 3
  },
  "delta_source_minus_stored_by_stream_abs": {
    "hb.market_data.v1": 1392,
    "hb.signal.v1": 1370,
    "hb.ml_signal.v1": 0,
    "hb.risk_decision.v1": 1281,
    "hb.execution_intent.v1": 1060,
    "hb.audit.v1": 0
  },
  "produced_since_baseline_by_stream": {
    "hb.market_data.v1": 13693,
    "hb.signal.v1": 13693,
    "hb.ml_signal.v1": 0,
    "hb.risk_decision.v1": 13693,
    "hb.execution_intent.v1": 13695,
    "hb.audit.v1": 2
  },
  "ingested_since_baseline_by_stream": {
    "hb.market_data.v1": 13692,
    "hb.signal.v1": 13692,
    "hb.ml_signal.v1": 0,
    "hb.risk_decision.v1": 13693,
    "hb.execution_intent.v1": 13695,
    "hb.audit.v1": 2
  },
  "delta_produced_minus_ingested_since_baseline": {
    "hb.market_data.v1": 1,
    "hb.signal.v1": 1,
    "hb.ml_signal.v1": 0,
    "hb.risk_decision.v1": 0,
    "hb.execution_intent.v1": 0,
    "hb.audit.v1": 0
  }
}