{
  "ts_utc": "2026-02-21T18:48:31.098350+00:00",
  "baseline_file": "/workspace/hbot/reports/event_store/baseline_counts.json",
  "stored_total_events": 403,
  "stored_events_by_stream": {
    "hb.audit.v1": 1,
    "hb.market_data.v1": 82,
    "hb.risk_decision.v1": 85,
    "hb.signal.v1": 20,
    "hb.execution_intent.v1": 215
  },
  "source_events_by_stream": {
    "hb.market_data.v1": 1430,
    "hb.signal.v1": 1345,
    "hb.ml_signal.v1": 0,
    "hb.risk_decision.v1": 1325,
    "hb.execution_intent.v1": 1240,
    "hb.audit.v1": 1
  },
  "delta_source_minus_stored_by_stream_abs": {
    "hb.market_data.v1": 1348,
    "hb.signal.v1": 1325,
    "hb.ml_signal.v1": 0,
    "hb.risk_decision.v1": 1240,
    "hb.execution_intent.v1": 1025,
    "hb.audit.v1": 0
  },
  "produced_since_baseline_by_stream": {
    "hb.market_data.v1": 731,
    "hb.signal.v1": 686,
    "hb.ml_signal.v1": 0,
    "hb.risk_decision.v1": 684,
    "hb.execution_intent.v1": 648,
    "hb.audit.v1": 0
  },
  "ingested_since_baseline_by_stream": {
    "hb.market_data.v1": 44,
    "hb.signal.v1": 2,
    "hb.ml_signal.v1": 0,
    "hb.risk_decision.v1": 36,
    "hb.execution_intent.v1": 119,
    "hb.audit.v1": 0
  },
  "delta_produced_minus_ingested_since_baseline": {
    "hb.market_data.v1": 687,
    "hb.signal.v1": 684,
    "hb.ml_signal.v1": 0,
    "hb.risk_decision.v1": 648,
    "hb.execution_intent.v1": 529,
    "hb.audit.v1": 0
  }
}