{
  "ts_utc": "2026-02-21T21:44:35.843896+00:00",
  "integrity_file": "/workspace/hbot/reports/event_store/integrity_20260221.json",
  "baseline_file": "/workspace/hbot/reports/event_store/baseline_counts.json",
  "stored_total_events": 42888,
  "stored_events_by_stream": {
    "hb.audit.v1": 1,
    "hb.market_data.v1": 10703,
    "hb.risk_decision.v1": 10706,
    "hb.signal.v1": 10638,
    "hb.execution_intent.v1": 10840
  },
  "source_events_by_stream": {
    "hb.market_data.v1": 12094,
    "hb.signal.v1": 12007,
    "hb.ml_signal.v1": 0,
    "hb.risk_decision.v1": 11987,
    "hb.execution_intent.v1": 11900,
    "hb.audit.v1": 1
  },
  "delta_source_minus_stored_by_stream_abs": {
    "hb.market_data.v1": 1391,
    "hb.signal.v1": 1369,
    "hb.ml_signal.v1": 0,
    "hb.risk_decision.v1": 1281,
    "hb.execution_intent.v1": 1060,
    "hb.audit.v1": 0
  },
  "produced_since_baseline_by_stream": {
    "hb.market_data.v1": 10615,
    "hb.signal.v1": 10615,
    "hb.ml_signal.v1": 0,
    "hb.risk_decision.v1": 10615,
    "hb.execution_intent.v1": 10615,
    "hb.audit.v1": 0
  },
  "ingested_since_baseline_by_stream": {
    "hb.market_data.v1": 10615,
    "hb.signal.v1": 10615,
    "hb.ml_signal.v1": 0,
    "hb.risk_decision.v1": 10615,
    "hb.execution_intent.v1": 10615,
    "hb.audit.v1": 0
  },
  "delta_produced_minus_ingested_since_baseline": {
    "hb.market_data.v1": 0,
    "hb.signal.v1": 0,
    "hb.ml_signal.v1": 0,
    "hb.risk_decision.v1": 0,
    "hb.execution_intent.v1": 0,
    "hb.audit.v1": 0
  }
}