{
  "ts_utc": "2026-02-21T21:19:29.482381+00:00",
  "integrity_file": "/workspace/hbot/reports/event_store/integrity_20260221.json",
  "baseline_file": "/workspace/hbot/reports/event_store/baseline_counts.json",
  "stored_total_events": 36784,
  "stored_events_by_stream": {
    "hb.audit.v1": 1,
    "hb.market_data.v1": 9177,
    "hb.risk_decision.v1": 9180,
    "hb.signal.v1": 9112,
    "hb.execution_intent.v1": 9314
  },
  "source_events_by_stream": {
    "hb.market_data.v1": 10566,
    "hb.signal.v1": 10479,
    "hb.ml_signal.v1": 0,
    "hb.risk_decision.v1": 10459,
    "hb.execution_intent.v1": 10372,
    "hb.audit.v1": 1
  },
  "delta_source_minus_stored_by_stream_abs": {
    "hb.market_data.v1": 1389,
    "hb.signal.v1": 1367,
    "hb.ml_signal.v1": 0,
    "hb.risk_decision.v1": 1279,
    "hb.execution_intent.v1": 1058,
    "hb.audit.v1": 0
  },
  "produced_since_baseline_by_stream": {
    "hb.market_data.v1": 9087,
    "hb.signal.v1": 9087,
    "hb.ml_signal.v1": 0,
    "hb.risk_decision.v1": 9087,
    "hb.execution_intent.v1": 9087,
    "hb.audit.v1": 0
  },
  "ingested_since_baseline_by_stream": {
    "hb.market_data.v1": 9089,
    "hb.signal.v1": 9089,
    "hb.ml_signal.v1": 0,
    "hb.risk_decision.v1": 9089,
    "hb.execution_intent.v1": 9089,
    "hb.audit.v1": 0
  },
  "delta_produced_minus_ingested_since_baseline": {
    "hb.market_data.v1": -2,
    "hb.signal.v1": -2,
    "hb.ml_signal.v1": 0,
    "hb.risk_decision.v1": -2,
    "hb.execution_intent.v1": -2,
    "hb.audit.v1": 0
  }
}