{
  "ts_utc": "2026-02-22T13:02:48.995200+00:00",
  "status": "FAIL",
  "critical_failures": [
    "event_store_integrity_freshness"
  ],
  "checks": [
    {
      "name": "preflight_checks",
      "severity": "critical",
      "pass": true,
      "reason": "required files present",
      "evidence_paths": [
        "F:\\Environement\\git-repo\\hummingbot_custo\\hbot\\config\\reconciliation_thresholds.json",
        "F:\\Environement\\git-repo\\hummingbot_custo\\hbot\\config\\parity_thresholds.json",
        "F:\\Environement\\git-repo\\hummingbot_custo\\hbot\\config\\portfolio_limits_v1.json",
        "F:\\Environement\\git-repo\\hummingbot_custo\\hbot\\config\\multi_bot_policy_v1.json",
        "F:\\Environement\\git-repo\\hummingbot_custo\\hbot\\scripts\\release\\run_backtest_regression.py",
        "F:\\Environement\\git-repo\\hummingbot_custo\\hbot\\scripts\\release\\run_replay_regression_cycle.py",
        "F:\\Environement\\git-repo\\hummingbot_custo\\hbot\\scripts\\release\\check_multi_bot_policy.py",
        "F:\\Environement\\git-repo\\hummingbot_custo\\hbot\\scripts\\release\\check_strategy_catalog_consistency.py",
        "F:\\Environement\\git-repo\\hummingbot_custo\\hbot\\scripts\\release\\run_tests.py",
        "F:\\Environement\\git-repo\\hummingbot_custo\\hbot\\scripts\\release\\run_secrets_hygiene_check.py",
        "F:\\Environement\\git-repo\\hummingbot_custo\\hbot\\docs\\validation\\backtest_regression_spec.md"
      ]
    },
    {
      "name": "multi_bot_policy_scope",
      "severity": "critical",
      "pass": true,
      "reason": "multi-bot policy scope is consistent across risk/reconciliation/account-map",
      "evidence_paths": [
        "F:\\Environement\\git-repo\\hummingbot_custo\\hbot\\reports\\policy\\latest.json",
        "F:\\Environement\\git-repo\\hummingbot_custo\\hbot\\config\\multi_bot_policy_v1.json"
      ]
    },
    {
      "name": "strategy_catalog_consistency",
      "severity": "critical",
      "pass": true,
      "reason": "strategy catalog configs resolve to shared code and declared bundles",
      "evidence_paths": [
        "F:\\Environement\\git-repo\\hummingbot_custo\\hbot\\reports\\strategy_catalog\\latest.json",
        "F:\\Environement\\git-repo\\hummingbot_custo\\hbot\\config\\strategy_catalog\\catalog_v1.json"
      ]
    },
    {
      "name": "unit_service_integration_tests",
      "severity": "critical",
      "pass": true,
      "reason": "deterministic test suite + coverage threshold passed",
      "evidence_paths": [
        "F:\\Environement\\git-repo\\hummingbot_custo\\hbot\\reports\\tests\\latest.json",
        "F:\\Environement\\git-repo\\hummingbot_custo\\hbot\\reports\\tests\\latest.md"
      ]
    },
    {
      "name": "secrets_hygiene",
      "severity": "critical",
      "pass": true,
      "reason": "no secret leakage markers in docs/reports/log artifacts",
      "evidence_paths": [
        "F:\\Environement\\git-repo\\hummingbot_custo\\hbot\\reports\\security\\latest.json",
        "F:\\Environement\\git-repo\\hummingbot_custo\\hbot\\scripts\\release\\run_secrets_hygiene_check.py"
      ]
    },
    {
      "name": "smoke_checks",
      "severity": "critical",
      "pass": true,
      "reason": "bot4 smoke activity artifacts found",
      "evidence_paths": [
        "F:\\Environement\\git-repo\\hummingbot_custo\\hbot\\data\\bot4\\logs\\epp_v24\\bot4_a\\minute.csv",
        "F:\\Environement\\git-repo\\hummingbot_custo\\hbot\\data\\bot4\\logs\\epp_v24\\bot4_d\\minute.csv"
      ]
    },
    {
      "name": "paper_smoke_matrix",
      "severity": "critical",
      "pass": true,
      "reason": "bot3 paper-mode intent verified",
      "evidence_paths": [
        "F:\\Environement\\git-repo\\hummingbot_custo\\hbot\\reports\\exchange_snapshots\\latest.json"
      ]
    },
    {
      "name": "replay_regression_cycle",
      "severity": "critical",
      "pass": true,
      "reason": "replay regression cycle PASS",
      "evidence_paths": [
        "F:\\Environement\\git-repo\\hummingbot_custo\\hbot\\reports\\replay_regression\\latest.json",
        "F:\\Environement\\git-repo\\hummingbot_custo\\hbot\\scripts\\release\\run_replay_regression_cycle.py"
      ]
    },
    {
      "name": "regression_backtest_harness",
      "severity": "critical",
      "pass": true,
      "reason": "regression harness PASS",
      "evidence_paths": [
        "F:\\Environement\\git-repo\\hummingbot_custo\\hbot\\reports\\backtest_regression\\latest.json",
        "F:\\Environement\\git-repo\\hummingbot_custo\\hbot\\scripts\\release\\run_backtest_regression.py"
      ]
    },
    {
      "name": "reconciliation_status",
      "severity": "critical",
      "pass": true,
      "reason": "reconciliation healthy and fresh",
      "evidence_paths": [
        "F:\\Environement\\git-repo\\hummingbot_custo\\hbot\\reports\\reconciliation\\latest.json"
      ]
    },
    {
      "name": "parity_thresholds",
      "severity": "critical",
      "pass": true,
      "reason": "parity pass and fresh",
      "evidence_paths": [
        "F:\\Environement\\git-repo\\hummingbot_custo\\hbot\\reports\\parity\\latest.json"
      ]
    },
    {
      "name": "portfolio_risk_status",
      "severity": "critical",
      "pass": true,
      "reason": "portfolio risk healthy and fresh",
      "evidence_paths": [
        "F:\\Environement\\git-repo\\hummingbot_custo\\hbot\\reports\\portfolio_risk\\latest.json"
      ]
    },
    {
      "name": "alerting_health",
      "severity": "critical",
      "pass": true,
      "reason": "alert webhook evidence is present/recent",
      "evidence_paths": [
        "F:\\Environement\\git-repo\\hummingbot_custo\\hbot\\reports\\reconciliation\\last_webhook_sent.json"
      ]
    },
    {
      "name": "event_store_integrity_freshness",
      "severity": "critical",
      "pass": false,
      "reason": "event store integrity missing/stale or missing correlations detected",
      "evidence_paths": [
        "F:\\Environement\\git-repo\\hummingbot_custo\\hbot\\reports\\event_store\\integrity_20260222.json"
      ]
    },
    {
      "name": "day2_event_store_gate",
      "severity": "critical",
      "pass": true,
      "reason": "day2 gate not yet GO",
      "evidence_paths": [
        "F:\\Environement\\git-repo\\hummingbot_custo\\hbot\\reports\\event_store\\day2_gate_eval_latest.json"
      ]
    }
  ],
  "release_manifest_ref": {
    "path": "F:\\Environement\\git-repo\\hummingbot_custo\\hbot\\docs\\ops\\release_manifest_20260221.md",
    "exists": true,
    "sha256": "da3131b9342c7d55630a88c306060a30fb88047b1a1c683c3d20a48d03d1e7e8",
    "size_bytes": 2864
  },
  "evidence_bundle": {
    "evidence_bundle_id": "f3d7a64c99556eea0b82f0c38057e253fb8737091eb77c7a33c21769f6a6e609",
    "artifact_count": 28,
    "artifacts": [
      {
        "path": "F:\\Environement\\git-repo\\hummingbot_custo\\hbot\\config\\multi_bot_policy_v1.json",
        "exists": true,
        "sha256": "eddded58c3923cbf14686e297084686d49b74ab0766565adbaeaf1270add35dd",
        "size_bytes": 2054
      },
      {
        "path": "F:\\Environement\\git-repo\\hummingbot_custo\\hbot\\config\\parity_thresholds.json",
        "exists": true,
        "sha256": "71cb2b0dbf461ba1b88191308b4daaadf2433740aaace9cf8197c9185d7c8224",
        "size_bytes": 1091
      },
      {
        "path": "F:\\Environement\\git-repo\\hummingbot_custo\\hbot\\config\\portfolio_limits_v1.json",
        "exists": true,
        "sha256": "e03aacc170d2a0dec6236846a3614d55316f3a1ee107f660e102f76f546dad03",
        "size_bytes": 373
      },
      {
        "path": "F:\\Environement\\git-repo\\hummingbot_custo\\hbot\\config\\reconciliation_thresholds.json",
        "exists": true,
        "sha256": "5ea94828eb8c5736c66a50d5c3331a87d9a4c14363d680813638dfa1be9519cc",
        "size_bytes": 784
      },
      {
        "path": "F:\\Environement\\git-repo\\hummingbot_custo\\hbot\\config\\strategy_catalog\\catalog_v1.json",
        "exists": true,
        "sha256": "2fbce9b3ede5a35e442824f982098e834d34950606521959e007e7f038ef5380",
        "size_bytes": 2833
      },
      {
        "path": "F:\\Environement\\git-repo\\hummingbot_custo\\hbot\\data\\bot4\\logs\\epp_v24\\bot4_a\\minute.csv",
        "exists": true,
        "sha256": "bd3e782ec0234a416337966ae43daab4536ddf08ac7b03aa8ce3234d2b77dda9",
        "size_bytes": 240244
      },
      {
        "path": "F:\\Environement\\git-repo\\hummingbot_custo\\hbot\\data\\bot4\\logs\\epp_v24\\bot4_d\\minute.csv",
        "exists": true,
        "sha256": "a9be7cdb628f2647c364dfcabb9f0fdff4780721d9dbeced6f5a4b4e793d0dbc",
        "size_bytes": 1944
      },
      {
        "path": "F:\\Environement\\git-repo\\hummingbot_custo\\hbot\\docs\\validation\\backtest_regression_spec.md",
        "exists": true,
        "sha256": "7fa32faa3844b80a566d3243a69b26ada9be74f8d66776a4fbd045e1b881acd9",
        "size_bytes": 5518
      },
      {
        "path": "F:\\Environement\\git-repo\\hummingbot_custo\\hbot\\reports\\backtest_regression\\latest.json",
        "exists": true,
        "sha256": "063f20760306edc5742b51b2716d7e791d3516c3e57097fac4005662bdf4e78c",
        "size_bytes": 2142
      },
      {
        "path": "F:\\Environement\\git-repo\\hummingbot_custo\\hbot\\reports\\event_store\\day2_gate_eval_latest.json",
        "exists": true,
        "sha256": "b75aeff13e96348f0cf688ba25d81a8271734831f66412fffa8de7022c0edcb8",
        "size_bytes": 753
      },
      {
        "path": "F:\\Environement\\git-repo\\hummingbot_custo\\hbot\\reports\\event_store\\integrity_20260222.json",
        "exists": true,
        "sha256": "a87bf09cd34cce96db006c97a06545c7a2fbd7fe46d6a2f519c1c06c16121d72",
        "size_bytes": 234
      },
      {
        "path": "F:\\Environement\\git-repo\\hummingbot_custo\\hbot\\reports\\exchange_snapshots\\latest.json",
        "exists": true,
        "sha256": "b949615ac4640945db8785f008e596246895e4f68b8ce39f593a30b9f139e232",
        "size_bytes": 1283
      },
      {
        "path": "F:\\Environement\\git-repo\\hummingbot_custo\\hbot\\reports\\parity\\latest.json",
        "exists": true,
        "sha256": "d5466f6ab30f539db38ef5979e7b65ba02453a033f2c0beeb4d562911d710fb6",
        "size_bytes": 2973
      },
      {
        "path": "F:\\Environement\\git-repo\\hummingbot_custo\\hbot\\reports\\policy\\latest.json",
        "exists": true,
        "sha256": "193211482d5a4ed9e029014b24a9696b4d0e15fcdbd3126868756000c5bf1286",
        "size_bytes": 897
      },
      {
        "path": "F:\\Environement\\git-repo\\hummingbot_custo\\hbot\\reports\\portfolio_risk\\latest.json",
        "exists": true,
        "sha256": "fb22ea037f1d73f928097d242fca2f2db29ef5171efa1ac9ebbef4d6bf6d5342",
        "size_bytes": 1725
      },
      {
        "path": "F:\\Environement\\git-repo\\hummingbot_custo\\hbot\\reports\\reconciliation\\last_webhook_sent.json",
        "exists": true,
        "sha256": "6071d8307c61a3e11d8838f6e633a0ca55a7aa2d6771205108da93487ca7c88d",
        "size_bytes": 125
      },
      {
        "path": "F:\\Environement\\git-repo\\hummingbot_custo\\hbot\\reports\\reconciliation\\latest.json",
        "exists": true,
        "sha256": "ea019a75055c67c0ab2acb70bdfe0481d019c5355048a861f14e60c111ab2433",
        "size_bytes": 2420
      },
      {
        "path": "F:\\Environement\\git-repo\\hummingbot_custo\\hbot\\reports\\replay_regression\\latest.json",
        "exists": true,
        "sha256": "716f98955906e99dbcc0f71fb0a50b59c82058480577791078d5de5c81e4c6d2",
        "size_bytes": 6587
      },
      {
        "path": "F:\\Environement\\git-repo\\hummingbot_custo\\hbot\\reports\\security\\latest.json",
        "exists": true,
        "sha256": "4477ead9f2c3236acbb9110f97f62c059d07ef4dd9ebffe699a98c0924578761",
        "size_bytes": 166
      },
      {
        "path": "F:\\Environement\\git-repo\\hummingbot_custo\\hbot\\reports\\strategy_catalog\\latest.json",
        "exists": true,
        "sha256": "8e829adc09f229ed6ed5dd809f3cb3a7ac74ac631e3a9d690dc60054187c10a0",
        "size_bytes": 801
      },
      {
        "path": "F:\\Environement\\git-repo\\hummingbot_custo\\hbot\\reports\\tests\\latest.json",
        "exists": true,
        "sha256": "396cc7169417d04ccfb60cbb3eaf9d3a5d7e6ec17c3ed6534a703fc2cdf39771",
        "size_bytes": 4266
      },
      {
        "path": "F:\\Environement\\git-repo\\hummingbot_custo\\hbot\\reports\\tests\\latest.md",
        "exists": true,
        "sha256": "d5a4cb979126516b7c7473426ae97777eb853c97cca137f685cd54d7d45f0cc6",
        "size_bytes": 3845
      },
      {
        "path": "F:\\Environement\\git-repo\\hummingbot_custo\\hbot\\scripts\\release\\check_multi_bot_policy.py",
        "exists": true,
        "sha256": "9c7b50f6ae693884964a9cc6234e38b670561e7a10399c04b459e8d651243ddc",
        "size_bytes": 6442
      },
      {
        "path": "F:\\Environement\\git-repo\\hummingbot_custo\\hbot\\scripts\\release\\check_strategy_catalog_consistency.py",
        "exists": true,
        "sha256": "b3efe7873369592ff0b5747406683765e547f9ce1bb888e66b226c998f1c0d2e",
        "size_bytes": 6163
      },
      {
        "path": "F:\\Environement\\git-repo\\hummingbot_custo\\hbot\\scripts\\release\\run_backtest_regression.py",
        "exists": true,
        "sha256": "b81418c240c277eebd1a685c103a77936d890ec8d763bc0d7412b0c86ca5ea64",
        "size_bytes": 8740
      },
      {
        "path": "F:\\Environement\\git-repo\\hummingbot_custo\\hbot\\scripts\\release\\run_replay_regression_cycle.py",
        "exists": true,
        "sha256": "c20f4bceef356a572433a936500007247e8a5d74fab6a18727ada4c28244d1cd",
        "size_bytes": 15053
      },
      {
        "path": "F:\\Environement\\git-repo\\hummingbot_custo\\hbot\\scripts\\release\\run_secrets_hygiene_check.py",
        "exists": true,
        "sha256": "ee612b9c38833b576330d88597dacc8b6bbeb02e8d357ff97d8e384a207e2e9c",
        "size_bytes": 5158
      },
      {
        "path": "F:\\Environement\\git-repo\\hummingbot_custo\\hbot\\scripts\\release\\run_tests.py",
        "exists": true,
        "sha256": "5156a5f50997aba7332de8c4349669fee9ad5c59fc5c45395c02790f258a8961",
        "size_bytes": 7594
      }
    ]
  },
  "notes": {
    "regression_runner_output": "",
    "replay_cycle_runner_output": "[replay-regression] status=pass\n[replay-regression] evidence=F:\\Environement\\git-repo\\hummingbot_custo\\hbot\\reports\\replay_regression\\replay_regression_20260222T130248Z.json",
    "multi_bot_policy_runner_output": "[multi-bot-policy] status=pass\n[multi-bot-policy] evidence=F:\\Environement\\git-repo\\hummingbot_custo\\hbot\\reports\\policy\\multi_bot_policy_check_20260222T130243Z.json",
    "strategy_catalog_runner_output": "[strategy-catalog] status=pass\n[strategy-catalog] evidence=F:\\Environement\\git-repo\\hummingbot_custo\\hbot\\reports\\strategy_catalog\\strategy_catalog_check_20260222T130243Z.json",
    "tests_runner_output": "[run-tests] status=pass\n[run-tests] rc=0\n[run-tests] evidence=F:\\Environement\\git-repo\\hummingbot_custo\\hbot\\reports\\tests\\test_run_20260222T130246Z.json",
    "secrets_hygiene_runner_output": "[secrets-hygiene] status=pass\n[secrets-hygiene] scanned_files=2161\n[secrets-hygiene] finding_count=0\n[secrets-hygiene] evidence=F:\\Environement\\git-repo\\hummingbot_custo\\hbot\\reports\\security\\secrets_hygiene_20260222T130247Z.json",
    "require_day2_go": false,
    "refresh_parity_once": true,
    "skip_replay_cycle": false,
    "ci_mode": true,
    "max_report_age_min": 15.0,
    "parity_refresh_rc": 0,
    "parity_refresh_output": ""
  }
}